tlab/__init__.py
tlab/geom.py
tlab/linalg.py
tlab/matrix.py
tlab/solver.py
tlab-0.1.10.dist-info/METADATA
tlab-0.1.10.dist-info/WHEEL
tlab-0.1.10.dist-info/RECORD
